pick/__init__.py
pick/py.typed
pick-2.3.1.dist-info/LICENSE
pick-2.3.1.dist-info/METADATA
pick-2.3.1.dist-info/WHEEL
pick-2.3.1.dist-info/RECORD
