Metadata-Version: 2.1
Name: pick
Version: 2.3.1
Summary: Pick an option in the terminal with a simple GUI
Home-page: https://github.com/aisk/pick
License: MIT
Keywords: terminal,gui
Author: wong2
Author-email: wonderfuly@gmail.com
Requires-Python: >=3.7
Classifier: License :: OSI Approved :: MIT License
Classifier: Programming Language :: Python :: 3
Classifier: Programming Language :: Python :: 3.7
Classifier: Programming Language :: Python :: 3.8
Classifier: Programming Language :: Python :: 3.9
Classifier: Programming Language :: Python :: 3.10
Classifier: Programming Language :: Python :: 3.11
Classifier: Programming Language :: Python :: 3.12
Requires-Dist: windows-curses (>=2.2.0,<3.0.0) ; sys_platform == "win32"
Project-URL: Repository, https://github.com/aisk/pick
